pymeshviewer/__init__.py
pymeshviewer/graph.py
pymeshviewer/meshviewerjson.py
pymeshviewer/node.py
pymeshviewer/nodecollection.py
pymeshviewer/nodesjson.py
pymeshviewer/parser.py
pymeshviewer/util.py
pymeshviewer-0.1.3.dist-info/LICENSE
pymeshviewer-0.1.3.dist-info/METADATA
pymeshviewer-0.1.3.dist-info/WHEEL
pymeshviewer-0.1.3.dist-info/top_level.txt
pymeshviewer-0.1.3.dist-info/RECORD
