Metadata-Version: 2.1
Name: pymeshviewer
Version: 0.1.3
Summary: Parser for Meshviewer nodelists and topology files
Home-page: https://github.com/blocktrron/pymeshviewer
Author: blocktrron
Author-email: david@darmstadt.freifunk.net
License: AGPLv3
Keywords: development meshviewer freifunk
Platform: UNKNOWN
Classifier: Development Status :: 3 - Alpha
Classifier: Intended Audience :: Developers
Classifier: Topic :: Utilities
Classifier: License :: OSI Approved :: GNU Affero General Public License v3
Classifier: Programming Language :: Python :: 3.5
Classifier: Programming Language :: Python :: 3.6
Requires-Dist: requests
